{"api_components_fields_slidercomponent.md":"de4f5cd1","api_components_contextcomponent.md":"088cd8fb","api_components_errorcomponent.md":"ab89105a","api_components_fields_togglecomponent.md":"0126692d","api_components_modalcomponent.md":"40989410","api_components_nodecomponent.md":"6c607feb","api_components_savecomponent.md":"bc14d931","api_components_fields_dangerbuttoncomponent.md":"43aea00b","api_components_fields_feedbackbuttoncomponent.md":"3022117b","api_components_fields_selectcomponent.md":"ace2bb01","api_components_layout_spacercomponent.md":"8e0b53af","api_components_fields_textcomponent.md":"039dbcea","api_components_layout_columncomponent.md":"0a31ce33","api_components_math_sqrtcomponent.md":"a610fb30","api_components_marknodecomponent.md":"95ce4d1c","api_components_hotkeycomponent.md":"94af8a77","api_components_infocomponent.md":"5e7ed906","api_components_layercomponent.md":"fb5a91af","api_components_layout_collapsiblecomponent.md":"b792d45f","api_components_layout_rowcomponent.md":"2f1b6079","api_components_math_floorcomponent.md":"765da36c","api_components_layout_stickycomponent.md":"3605e970","api_components_layout_verticalrulecomponent.md":"87270803","api_modules_data_common.md":"91d11f70","api_modules_data_themes.md":"4088bd49","api_modules_data_projentry.md":"79aeaa73","api_modules_features_achievement.md":"cd26a191","api_modules_features_action.md":"b7aae132","api_modules_features_tabs_tabfamily.md":"7edfe3b4","api_modules_features_tooltip.md":"8f77999a","api_modules_features_tree.md":"f908ac10","api_modules_features_upgrade.md":"3a568bd3","api_modules_game_player.md":"0ff6beaf","api_modules_game_requirements.md":"2b28e2e9","api_modules_game_settings.md":"9806c3bd","api_modules_game_state.md":"3ac54075","api_modules_lib_break_eternity.md":"2c1c3614","api_modules_lib_collapsetransition.md":"37a925e1","api_modules_lib_lru-cache.md":"9af07d85","api_modules_lib_pixi.md":"2b426252","api_modules_lib_pwa-register.md":"e2eb20d6","api_modules_game_formulas_types.md":"6d408340","guide_creating-your-project_project-info.md":"c56eeb0f","guide_creating-your-project_themes.md":"270c3647","api_modules_util_bignum.md":"b4aab637","guide_creating-your-project_utils.md":"4760f329","api_modules_util_break_eternity.md":"2a80a12c","guide_getting-started_first-layer.md":"eea178cb","api_modules_game_gameloop.md":"ea9bda9a","api_modules_util_save.md":"2a100674","api_modules_lib_vue-panzoom.md":"bfc32ff5","api_modules_lib_vue-textarea-autosize.md":"a92591ec","guide_advanced-concepts_dynamic-layers.md":"9ec766d2","api_modules_features_challenge.md":"bd858f4a","guide_important-concepts_features.md":"b922ebcf","guide_important-concepts_persistence.md":"8c085a8c","guide_important-concepts_reactivity.md":"6a2d1084","guide_important-concepts_requirements.md":"9e8fd070","api_modules_features_bar.md":"9604d286","guide_index.md":"a9606b78","guide_migrations_0-6.md":"575646c4","api_modules_features_grid.md":"ffe71f11","guide_recipes_particles.md":"72bcff9c","guide_recipes_prestige.md":"ea2e4e7b","api_modules_features_infobox.md":"90113df9","guide_recipes_save-progress.md":"4d79827f","api_modules_game_modifiers.md":"f8a2c59e","api_modules_game_layers.md":"4ab34e80","api_modules_util_computed.md":"ba2689a0","api_modules_util_vue.md":"e8d7d97d","api_modules_game_persistence.md":"b82aac95","api_modules_game_notifications.md":"9a314c38","guide_important-concepts_formulas.md":"63bf13f7","api_modules_features_board.md":"31b80d8b","api_modules_features_feature.md":"4e98e178","api_modules_features_hotkey.md":"3577c6d9","api_modules_game_formulas_operations.md":"e8e4806b","api_modules_features_clickable.md":"d29a69c7","api_modules_features_tabs_tab.md":"b0d897cf","api_modules_features_decorators_bonusdecorator.md":"64718150","api_modules_features_decorators_common.md":"67d252c2","api_modules_features_links.md":"26fc907d","api_modules_features_conversion.md":"970ccc3a","guide_advanced-concepts_nodes.md":"92611da2","api_modules_features_repeatable.md":"e63148c4","api_modules_features_reset.md":"4c6103be","api_modules_features_resource.md":"8ae1f501","api_modules_game_events.md":"a9031949","api_modules_util_proxies.md":"92fedcf7","guide_advanced-concepts_creating-features.md":"88ee9059","guide_creating-your-project_changelog.md":"d8a46ee2","api_modules_util_common.md":"79f6c939","guide_important-concepts_coercable.md":"4ac1576c","api_overview.md":"88cceb38","guide_getting-started_examples.md":"8f3101eb","api_modules_features_particles.md":"299b8355","api_modules_game_formulas_formulas.md":"a85fa039","guide_creating-your-project_project-entry.md":"58e6fdcf","guide_getting-started_setup.md":"f1d88449","index.md":"d8bea653","guide_getting-started_updating.md":"ec3df0e8","guide_important-concepts_layers.md":"ca5bd4ed"}
